[
  {
    "id": 5424,
    "title": "[짱구] 세트로도 즐겨요#댄꼼마 짱구 오또카지 후드&스웨트팬츠(2컬러)",
    "price": "15800",
    "participants": 117,
    "rating": "4.6",
    "reviewCount": "7",
    "deliverFee" : 0,
    "difficultDeliverFee" : 5000,
    "image": "https://cdn2.wadiz.kr/2023/12/11/f064af90-e30f-41eb-8856-b6c3f6213fac.jpg/wadiz/resize/1200/format/jpg/quality/80/",
    "category" : "애니메이션",
    "subCategory" : "세트",
    "options" : [{"name": "<짱구> 오토카지 후드티셔츠-멜란지 그레이", "price": 59900 },
    {"name": "<짱구>1992얼굴자수 스웨트팬츠-멜란지 그레이", "price": 49900 },
    {"name": "<짱구> 1992 얼굴자수 스웨트팬츠-크림", "price": 49900 }
  ],
    "maker": "댄꼼마",
    "makerIsSuperMaker" : true,
    "makerIsTop100" : true,
    "makerImage" : "https://cdn2.wadiz.kr/2023/11/29/c7c008b8-2b79-4ab3-aac2-5f1d659c02f1.jpg/wadiz/resize/100/format/jpg/quality/90/",
    "makerRating" : 5.0,
    "makerReviewCount" : 999,
    "makerTotalFunding" :"19억원",
    "makerFollowerCount": 29139,
    "makerSupporter" : 35557
  },

    {
    "id": 11352,
    "title": "더 이상 가방에서 립스틱 찾지 마세요.[가방+파우치], yyeon",
    "price": "135000",
    "participants": 1261,
    "rating": "4.9",
    "reviewCount": "73",
    "deliverFee" : 0,
    "difficultDeliverFee" : 5000,
    "image": "https://cdn2.wadiz.kr/2025/06/30/a9619d62-4aea-41ae-b3f0-ad28bd528e7f.jpg/wadiz/resize/1200/format/jpg/quality/80/",
    "category" : "가방",
    "subCategory" : "선물",
    "options" : [{"name": "블루밍백(컬러선택)", "price": 135000 },
    {"name": "체인 스트랩", "price": 12900 }
  ],
    "maker": "yyeon,",
    "makerIsSuperMaker" : true,
    "makerIsTop100" : false,
    "makerImage" : "https://cdn2.wadiz.kr/2025/06/16/6533e16c-3c7d-44ab-9972-2fce2c5adb21.png/wadiz/resize/100/format/jpg/quality/90/",
    "makerRating" : 5.0,
    "makerReviewCount" : 481,
    "makerTotalFunding" :"9억원",
    "makerFollowerCount": 5293,
    "makerSupporter" : 7220
  }
]